netbox_file_upload/__init__.py
netbox_file_upload/admin.py
netbox_file_upload/forms.py
netbox_file_upload/models.py
netbox_file_upload/navigation.py
netbox_file_upload/template_content.py
netbox_file_upload/urls.py
netbox_file_upload/views.py
netbox_file_upload/api/__init__.py
netbox_file_upload/api/serializers.py
netbox_file_upload/api/urls.py
netbox_file_upload/api/views.py
netbox_file_upload/templates/.DS_Store
netbox_file_upload/templates/netbox_file_upload/device_list.html
netbox_file_upload/templates/netbox_file_upload/file.html
netbox_file_upload-0.11.dist-info/METADATA
netbox_file_upload-0.11.dist-info/WHEEL
netbox_file_upload-0.11.dist-info/top_level.txt
netbox_file_upload-0.11.dist-info/RECORD
