Metadata-Version: 2.1
Name: netbox-file-upload
Version: 0.11
Summary: A file upload plugin for Netbox
Home-page: UNKNOWN
Author: Seam Collins
Author-email: UNKNOWN
License: Apache 2.0
Platform: UNKNOWN
